Workbook
Name EPICS_ESTIMATE: GITHUB_EPICS!$F$2:$F$62
Name EPICS_PERIOD: GITHUB_EPICS!$G$2:$G$62
Name EPICS_STATUS: GITHUB_EPICS!$D$2:$D$62
Name EPICS_TYPE: GITHUB_EPICS!$E$2:$E$62
Name PERIODS: Parameters!$A$6:$A$46
Name PLANNING: Parameters!$A$6:$J$12

Sheet Parameters
A1: Capacity planning for Alkemio
A2: This tab provides teams' velocity and overall releases capacity overview based on the current version of 2015 release calendar.
A4: Time Period | B4: Time Period Start | C4: Time Period End | D4: Features allocation, % | E4: Development Sprints available | F4: Vacations / Done (sprints) | G4: Available Sprints | H4: Points / sprint | I4: Capacity | J4: Comments
A6: 2023 Q1 | B6: 44928 | C6: 45012 | D6: 0.8 | E6: =(C6-B6)/7/2 -> 6 | F6: 6 | G6: =E6-F6 -> 0 | H6: 200 | I6: =H6*G6*D6 -> 0
A7: 2023 Q2 | B7: =C6 -> 45012 | C7: 45096 | D7: 0.8 | E7: =(C7-B7)/7/2 -> 6 | F7: 6 | G7: =E7-F7 -> 0 | H7: 200 | I7: =H7*G7*D7 -> 0 | M7: Note: update to have each period start / end adjustable
A8: 2023 Q3 | B8: =C7 -> 45096 | C8: 45194 | D8: 0.6 | E8: =(C8-B8)/7/2 -> 7 | F8: 5.5 | G8: =E8-F8 -> 1.5 | H8: 200 | I8: =H8*G8*D8 -> 180
A9: 2023 Q4 | B9: =C8 -> 45194 | C9: 45292 | D9: 0.5 | E9: =(C9-B9)/7/2 -> 7 | F9: 0.5 | G9: =E9-F9 -> 6.5 | H9: 200 | I9: =H9*G9*D9 -> 650
A10: 2024 Q1 | B10: =C9 -> 45292 | C10: 45383 | D10: 0.5 | E10: =(C10-B10)/7/2 -> 6.5 | F10: 0.5 | G10: =E10-F10 -> 6 | H10: 200 | I10: =H10*G10*D10 -> 600
A11: 2024 Q2 | B11: =C10 -> 45383 | C11: 45474 | D11: 0.5 | E11: =(C11-B11)/7/2 -> 6.5 | F11: 0.5 | G11: =E11-F11 -> 6 | H11: 200 | I11: =H11*G11*D11 -> 600
A12: 2024 H2 | B12: =C11 -> 45474 | C12: 45657 | D12: 0.5 | E12: =(C12-B12)/7/2 -> 13.071429 | G12: =E12-F12 -> 13.071429 | H12: 200 | I12: =H12*G12*D12 -> 1307.1429

Sheet Capacity
A4: Delivery | B4: Planned | C4: Available | D4: Done | E4: Total | F4: Functionality: Tactical | G4: Maintenance | H4: Operations: Security | I4: Operations: Effectiveness | J4: Usability | K4: Performance | L4: Functionality: Strategic | M4: Not specified
A5: 2023 Q1 | B5: =SUMIFS(EPICS_ESTIMATE, EPICS_PERIOD, $A5, EPICS_STATUS, "<>Done") -> 0 | C5: =Parameters!I6 -> 0 | D5: =SUMIFS(EPICS_ESTIMATE, EPICS_PERIOD, $A5, EPICS_STATUS, "Done") -> 0 | E5: =SUM(#REF!, #REF!) -> #REF! | F5: =SUMIFS(EPICS_ESTIMATE, EPICS_PERIOD, $A5, EPICS_TYPE, F$4) -> 0 | G5: =SUMIFS(EPICS_ESTIMATE, EPICS_PERIOD, $A5, EPICS_TYPE, G$4) -> 0 | H5: =SUMIFS(EPICS_ESTIMATE, EPICS_PERIOD, $A5, EPICS_TYPE, H$4) -> 0 | I5: =SUMIFS(EPICS_ESTIMATE, EPICS_PERIOD, $A5, EPICS_TYPE, I$4) -> 0 | J5: =SUMIFS(EPICS_ESTIMATE, EPICS_PERIOD, $A5, EPICS_TYPE, J$4) -> 0 | K5: =SUMIFS(EPICS_ESTIMATE, EPICS_PERIOD, $A5, EPICS_TYPE, K$4) -> 0 | L5: =SUMIFS(EPICS_ESTIMATE, EPICS_PERIOD, $A5, EPICS_TYPE, L$4) -> 0 | M5: =#REF!-SUM(F5:L5) -> #REF!
A6: 2023 Q2 | B6: =SUMIFS(EPICS_ESTIMATE, EPICS_PERIOD, $A6, EPICS_STATUS, "<>Done") -> 0 | C6: =Parameters!I7 -> 0 | D6: =SUMIFS(EPICS_ESTIMATE, EPICS_PERIOD, $A6, EPICS_STATUS, "Done") -> 0 | E6: =SUM(#REF!, #REF!) -> #REF! | F6: =SUMIFS(EPICS_ESTIMATE, EPICS_PERIOD, $A6, EPICS_TYPE, F$4) -> 0 | G6: =SUMIFS(EPICS_ESTIMATE, EPICS_PERIOD, $A6, EPICS_TYPE, G$4) -> 0 | H6: =SUMIFS(EPICS_ESTIMATE, EPICS_PERIOD, $A6, EPICS_TYPE, H$4) -> 0 | I6: =SUMIFS(EPICS_ESTIMATE, EPICS_PERIOD, $A6, EPICS_TYPE, I$4) -> 0 | J6: =SUMIFS(EPICS_ESTIMATE, EPICS_PERIOD, $A6, EPICS_TYPE, J$4) -> 0 | K6: =SUMIFS(EPICS_ESTIMATE, EPICS_PERIOD, $A6, EPICS_TYPE, K$4) -> 0 | L6: =SUMIFS(EPICS_ESTIMATE, EPICS_PERIOD, $A6, EPICS_TYPE, L$4) -> 0 | M6: =#REF!-SUM(F6:L6) -> #REF!
A7: =Parameters!A8 -> 2023 Q3 | B7: =SUMIFS(EPICS_ESTIMATE, EPICS_PERIOD, $A7, EPICS_STATUS, "<>Done") -> 0 | C7: =Parameters!I8 -> 180 | D7: =SUMIFS(EPICS_ESTIMATE, EPICS_PERIOD, $A7, EPICS_STATUS, "Done") -> 0 | E7: =SUM(#REF!, #REF!) -> #REF! | F7: =SUMIFS(EPICS_ESTIMATE, EPICS_PERIOD, $A7, EPICS_TYPE, F$4) -> 0 | G7: =SUMIFS(EPICS_ESTIMATE, EPICS_PERIOD, $A7, EPICS_TYPE, G$4) -> 0 | H7: =SUMIFS(EPICS_ESTIMATE, EPICS_PERIOD, $A7, EPICS_TYPE, H$4) -> 0 | I7: =SUMIFS(EPICS_ESTIMATE, EPICS_PERIOD, $A7, EPICS_TYPE, I$4) -> 0 | J7: =SUMIFS(EPICS_ESTIMATE, EPICS_PERIOD, $A7, EPICS_TYPE, J$4) -> 0 | K7: =SUMIFS(EPICS_ESTIMATE, EPICS_PERIOD, $A7, EPICS_TYPE, K$4) -> 0 | L7: =SUMIFS(EPICS_ESTIMATE, EPICS_PERIOD, $A7, EPICS_TYPE, L$4) -> 0 | M7: =#REF!-SUM(F7:L7) -> #REF!
A8: =Parameters!A9 -> 2023 Q4 | B8: =SUMIFS(EPICS_ESTIMATE, EPICS_PERIOD, $A8, EPICS_STATUS, "<>Done") -> 0 | C8: =Parameters!I9 -> 650 | D8: =SUMIFS(EPICS_ESTIMATE, EPICS_PERIOD, $A8, EPICS_STATUS, "Done") -> 0 | E8: =SUM(#REF!, #REF!) -> #REF! | F8: =SUMIFS(EPICS_ESTIMATE, EPICS_PERIOD, $A8, EPICS_TYPE, F$4) -> 0 | G8: =SUMIFS(EPICS_ESTIMATE, EPICS_PERIOD, $A8, EPICS_TYPE, G$4) -> 0 | H8: =SUMIFS(EPICS_ESTIMATE, EPICS_PERIOD, $A8, EPICS_TYPE, H$4) -> 0 | I8: =SUMIFS(EPICS_ESTIMATE, EPICS_PERIOD, $A8, EPICS_TYPE, I$4) -> 0 | J8: =SUMIFS(EPICS_ESTIMATE, EPICS_PERIOD, $A8, EPICS_TYPE, J$4) -> 0 | K8: =SUMIFS(EPICS_ESTIMATE, EPICS_PERIOD, $A8, EPICS_TYPE, K$4) -> 0 | L8: =SUMIFS(EPICS_ESTIMATE, EPICS_PERIOD, $A8, EPICS_TYPE, L$4) -> 0 | M8: =#REF!-SUM(F8:L8) -> #REF!
A9: 2024 Q1 | B9: =SUMIFS(EPICS_ESTIMATE, EPICS_PERIOD, $A9, EPICS_STATUS, "<>Done") -> 0 | C9: =Parameters!I10 -> 600 | D9: =SUMIFS(EPICS_ESTIMATE, EPICS_PERIOD, $A9, EPICS_STATUS, "Done") -> 0 | E9: =SUM(#REF!, #REF!) -> #REF! | F9: =SUMIFS(EPICS_ESTIMATE, EPICS_PERIOD, $A9, EPICS_TYPE, F$4) -> 0 | G9: =SUMIFS(EPICS_ESTIMATE, EPICS_PERIOD, $A9, EPICS_TYPE, G$4, EPICS_STATUS, "<>Done") -> 0 | H9: =SUMIFS(EPICS_ESTIMATE, EPICS_PERIOD, $A9, EPICS_TYPE, H$4, EPICS_STATUS, "<>Done") -> 0 | I9: =SUMIFS(EPICS_ESTIMATE, EPICS_PERIOD, $A9, EPICS_TYPE, I$4, EPICS_STATUS, "<>Done") -> 0 | J9: =SUMIFS(EPICS_ESTIMATE, EPICS_PERIOD, $A9, EPICS_TYPE, J$4, EPICS_STATUS, "<>Done") -> 0 | K9: =SUMIFS(EPICS_ESTIMATE, EPICS_PERIOD, $A9, EPICS_TYPE, K$4, EPICS_STATUS, "<>Done") -> 0 | L9: =SUMIFS(EPICS_ESTIMATE, EPICS_PERIOD, $A9, EPICS_TYPE, L$4, EPICS_STATUS, "<>Done") -> 0 | M9: =#REF!-SUM(F9:L9) -> #REF!
A10: 2024 Q2 | B10: =SUMIFS(EPICS_ESTIMATE, EPICS_PERIOD, $A10, EPICS_STATUS, "<>Done") -> 0 | C10: =Parameters!I10 -> 600 | D10: =SUMIFS(EPICS_ESTIMATE, EPICS_PERIOD, $A10, EPICS_STATUS, "Done") -> 0 | E10: =SUM(#REF!, #REF!) -> #REF! | F10: =SUMIFS(EPICS_ESTIMATE, EPICS_PERIOD, $A10, EPICS_TYPE, F$4) -> 0 | G10: =SUMIFS(EPICS_ESTIMATE, EPICS_PERIOD, $A10, EPICS_TYPE, G$4, EPICS_STATUS, "<>Done") -> 0 | H10: =SUMIFS(EPICS_ESTIMATE, EPICS_PERIOD, $A10, EPICS_TYPE, H$4, EPICS_STATUS, "<>Done") -> 0 | I10: =SUMIFS(EPICS_ESTIMATE, EPICS_PERIOD, $A10, EPICS_TYPE, I$4, EPICS_STATUS, "<>Done") -> 0 | J10: =SUMIFS(EPICS_ESTIMATE, EPICS_PERIOD, $A10, EPICS_TYPE, J$4, EPICS_STATUS, "<>Done") -> 0 | K10: =SUMIFS(EPICS_ESTIMATE, EPICS_PERIOD, $A10, EPICS_TYPE, K$4, EPICS_STATUS, "<>Done") -> 0 | L10: =SUMIFS(EPICS_ESTIMATE, EPICS_PERIOD, $A10, EPICS_TYPE, L$4, EPICS_STATUS, "<>Done") -> 0 | M10: =#REF!-SUM(F10:L10) -> #REF!
A11: =Parameters!A12 -> 2024 H2 | B11: =SUMIFS(EPICS_ESTIMATE, EPICS_PERIOD, $A11, EPICS_STATUS, "<>Done") -> 0 | C11: =Parameters!I12 -> 1307.1429 | D11: =SUMIFS(EPICS_ESTIMATE, EPICS_PERIOD, $A11, EPICS_STATUS, "Done") -> 0 | E11: =SUM(#REF!, #REF!) -> #REF! | F11: =SUMIFS(EPICS_ESTIMATE, EPICS_PERIOD, $A11, EPICS_TYPE, F$4) -> 0 | G11: =SUMIFS(EPICS_ESTIMATE, EPICS_PERIOD, $A11, EPICS_TYPE, G$4, EPICS_STATUS, "<>Done") -> 0 | H11: =SUMIFS(EPICS_ESTIMATE, EPICS_PERIOD, $A11, EPICS_TYPE, H$4, EPICS_STATUS, "<>Done") -> 0 | I11: =SUMIFS(EPICS_ESTIMATE, EPICS_PERIOD, $A11, EPICS_TYPE, I$4, EPICS_STATUS, "<>Done") -> 0 | J11: =SUMIFS(EPICS_ESTIMATE, EPICS_PERIOD, $A11, EPICS_TYPE, J$4, EPICS_STATUS, "<>Done") -> 0 | K11: =SUMIFS(EPICS_ESTIMATE, EPICS_PERIOD, $A11, EPICS_TYPE, K$4, EPICS_STATUS, "<>Done") -> 0 | L11: =SUMIFS(EPICS_ESTIMATE, EPICS_PERIOD, $A11, EPICS_TYPE, L$4, EPICS_STATUS, "<>Done") -> 0 | M11: =#REF!-SUM(F11:L11) -> #REF!

Sheet GITHUB_EPICS
A1: Assignees | B1: Repository | C1: Labels | D1: Title | E1: Status | F1: Sprint | G1: Milestone | H1: Period | I1: EpicPoints | J1: Partner | K1: SprintPoints | L1: Milestone
B2: alkemio | C2: Epic | D2: Client Tech debt: Q4 2025 | E2: Being defined
B3: alkemio | C3: Epic | D3: Working on Alkemio as an Organization | E3: Being defined | F3: 2025-10-28
A4: Evgeni Dimitrov | B4: alkemio | C4: Epic,QA | D4: QA: Test Suites extensions Q4 | E4: Being defined | G4: Improved Confidence in the Platform | H4: 2024 Q3
B5: alkemio | C5: Epic | D5: Whiteboards: Robustness + performance Q4 | E5: Being defined | G5: Improved Confidence in the Platform
B6: alkemio | C6: Epic,QA,Product Discussion,Rhea Team | D6: QA on multi-user collaboration on whiteboard | E6: Being defined | F6: 2025-10-28 | G6: Improved Confidence in the Platform | H6: 2024 Q2 | K6: 13
A7: Svetoslav Petkov,user | B7: alkemio | C7: Epic | D7: Reporting: (automated) sharing of reports , read only access | E7: Being defined | H7: 2024 Q2 | I7: 20
B8: alkemio | C8: Epic,Roadmap Candidate | D8: Client component library in Figma | E8: Being defined | H8: 2024 Q2 | K8: 8
B9: alkemio | C9: Epic | D9: Simpler URLs | E9: Being defined | G9: Spaces with Subspaces | H9: 2024 Q3
A10: Valentin Yanakiev | B10: alkemio | C10: Epic,Infrastructure | D10: Storage management | E10: Being defined | F10: 2025-10-28 | H10: 2024 Q3
B11: alkemio | C11: Initiative | D11: I: Analytics via connectivity graph v1 | E11: Being defined
B12: alkemio | C12: Initiative | D12: I: Maintainability | E12: Being defined
B13: alkemio | C13: Initiative | D13: I: Journey structure refresh | E13: Being defined | F13: 2023-03-14
B14: alkemio | C14: Initiative | D14: Innovation library - Agreements | E14: Being defined
B15: alkemio | C15: Initiative | D15: I: Onboarding the community | E15: Being defined
B16: alkemio | C16: Initiative | D16: I: Innovation Hubs | E16: Being defined
B17: alkemio | C17: Initiative | D17: I: Platform responsiveness | E17: Being defined
B18: alkemio | C18: Initiative | D18: I: Guidance for users | E18: Being defined
B19: alkemio | C19: Initiative | D19: I: Platform Management | E19: Being defined
B20: alkemio | C20: Initiative | D20: I: Accessibility | E20: Being defined
B21: alkemio | C21: Initiative | D21: I: Content + Knowledge Management | E21: Being defined
B22: alkemio | C22: Initiative | D22: I: Notifications | E22: Being defined
B23: alkemio | C23: Initiative | D23: I: Library population, usage + feedback | E23: Being defined
B24: alkemio | C24: Initiative | D24: Content on the platform | E24: Being defined
B25: alkemio | C25: Initiative | D25: I: Innovation Library | E25: Being defined
... B29: alkemio | C29: Epic | D29: Bucket: Enhancing UX: Visual improvements | E29: Being defined
A30: Bobby Kolev | B30: alkemio | C30: Epic | D30: Video calling services | E30: Being elaborated | F30: 2025-09-16
A31: Bobby Kolev,Svetoslav Petkov | B31: alkemio | C31: Epic | D31: Notifications: Controls per space | E31: Being elaborated | F31: 2025-10-14 | G31: Notifications: on the platform, per space | H31: 2024 Q2
B32: alkemio | C32: Epic | D32: Notifications: Grouping + additional types | E32: Being elaborated | F32: 2025-10-28 | G32: Notifications: on the platform, per space | H32: 2024 Q2 | I32: 50
A33: Polina Boneva | B33: alkemio | C33: Epic,client | D33: Accessibility: WCAG 2.1 | E33: Being elaborated | F33: 2025-09-30
B34: alkemio | C34: Epic | D34: Templates: Interaction Space library and platform library | E34: Being elaborated | F34: 2025-09-16 | G34: Templates: Complete set | H34: 2024 Q2 | I34: 30
A35: Valentin Yanakiev | B35: alkemio | C35: Epic | D35: Sharing/Collaborating in callouts with unauthenticated users | E35: Being elaborated | F35: 2025-09-16
A36: Valentin Yanakiev | B36: alkemio | C36: Epic,Atlas Team,Rhea Team | D36: Independent issues | E36: Being elaborated | F36: 2025-09-16
B37: alkemio | C37: Epic | D37: Calendar events Bucket: Importing/Exporting; flexible time; show events from related sub/space | E37: Being elaborated | F37: 2025-10-14 | H37: 2024 Q3
B38: infrastructure-operations | C38: operations,Epic,Infrastructure | D38: External Penetration Testing [Q4 2025] | E38: Being elaborated | F38: 2025-10-14 | J38: Avans
B39: alkemio | C39: Epic | D39: Subscriptions on all Space pages | E39: Being elaborated | F39: 2025-10-28
B40: alkemio | C40: Epic,Roadmap Discussion,New this Sprint | D40: Licensing: Account management | E40: Being elaborated | F40: 2025-10-14 | G40: Products + Licensing
B41: alkemio | C41: Epic | D41: Flexible & Templatable community roles | E41: Being elaborated | G41: Innovation Professional Support | H41: 2024 Q2 | I41: 30
B42: alkemio | C42: Epic | D42: VC: Single user interaction | E42: Being elaborated
B43: alkemio | C43: Epic,Product Team | D43: Space layout | E43: Being elaborated | F43: 2025-10-28
A44: Valentin Yanakiev | B44: alkemio | C44: Epic | D44: Infrastructure: Maintainability | E44: Being elaborated | G44: Improved Confidence in the Platform | H44: 2024 Q2 | I44: 30
B45: alkemio | C45: Epic | D45: Authorization Checking Service; cleanup | E45: Being elaborated | H45: 2024 Q2
B46: alkemio | C46: Epic,Product Discussion | D46: Private sub-subspace | E46: Being elaborated | G46: Spaces with Subspaces | H46: 2024 Q2 | I46: 20
B47: alkemio | C47: Epic,Roadmap Discussion | D47: Refresh Contributors page | E47: Being elaborated | H47: 2024 Q2 | I47: 20
B48: alkemio | C48: Epic,Roadmap Discussion | D48: Bucket: Content editing improvements | E48: Being elaborated | H48: 2024 Q2 | I48: 20
B49: alkemio | C49: Epic | D49: Activity tracking: deletion | E49: Being elaborated | H49: 2024 Q2 | I49: 30
B50: alkemio | C50: Epic,Roadmap Discussion | D50: InnovationFlow: Creation + management | E50: Being elaborated | H50: 2024 Q2 | I50: 80
B51: alkemio | C51: Epic | D51: Using Temporary Storage | E51: Being elaborated
B52: alkemio | C52: Epic | D52: Enhance Tag Management and Usability | E52: Being elaborated
B53: alkemio | C53: Epic | D53: Bucket: User Documentation | E53: Being elaborated
A54: Simone | B54: alkemio | C54: Epic,Rhea Team | D54: Fixing MD editor bugs | E54: Defined | F54: 2025-10-28
B55: alkemio | C55: Epic | D55: VCs: Monitoring + operations | E55: Defined | G55: Virtual Contributors: Q3 2024 | H55: 2024 Q3
B56: alkemio | C56: Epic,Product Team | D56: Memberships: consistency, organization | E56: Defined | G56: Create your own Space: GA
B57: alkemio | C57: Epic | D57: Authentication: Identity Management | E57: Defined | G57: Create your own Space: GA | H57: 2024 Q3
A58: Valentin Yanakiev,Svetoslav Petkov | B58: alkemio | C58: Epic | D58: API usage performance / monitoring / audit trail | E58: Defined | G58: Improved Confidence in the Platform | H58: 2024 Q3
B59: alkemio | C59: Epic | D59: Platform Administration | E59: Defined
B60: alkemio | C60: Epic,Roadmap Discussion,Product Discussion | D60: Journey settings: challenge, community membership policy | E60: Defined | H60: 2024 Q2 | I60: 20
B61: alkemio | C61: Epic,Atlas Team | D61: Licensing: Runtime enforcement | E61: Defined | G61: Create your own Space: GA | H61: 2024 Q3
B62: alkemio | C62: Epic,QA | D62: QA: Test suite user authentication flows | E62: Defined | H62: 2024 Q2 | I62: 30
B63: alkemio | C63: Epic,Atlas Team | D63: VC: Expert engine space data retrieval + loading | E63: Elaborated | G63: Virtual Contributors: Q3 2024 | H63: 2024 Q3
B64: alkemio | C64: Epic | D64: Forum: ready for release notes | E64: Elaborated | H64: 2024 Q2
B65: alkemio | C65: Epic | D65: Bucket: Server performance | E65: Icebox
B66: alkemio | C66: Epic | D66: Welcome dialog for new members of a Journey | E66: Icebox
B67: alkemio | C67: Epic | D67: Bucket: Enhancing UX: Reducing Clicks and Scrolling | E67: Icebox
B68: alkemio | C68: Epic | D68: Bucket: Enhancing UX: Guidance in current functionality | E68: Icebox
B69: alkemio | C69: Epic | D69: Bucket: Forum improvements | E69: Icebox
B70: alkemio | C70: Epic | D70: Bucket: Enhancing UX: Streamlining User Interaction with Existing Functionality | E70: Icebox
B71: alkemio | C71: Epic,Product Team,client | D71: UX: Sorting control on the client | E71: Icebox
B72: alkemio | C72: Epic | D72: Bucket: Journey membership UX improvements | E72: Icebox
B73: alkemio | C73: Epic | D73: Bucket: User login / membership improvements | E73: Icebox
B74: infrastructure-operations | C74: operations,Epic,Infrastructure | D74: Reporting: geolocation, sign ups | E74: Icebox
B75: alkemio | C75: Epic | D75: Knowledge: Suggested best practice templates | E75: Icebox
B76: alkemio | C76: Epic,Product Discussion | D76: Activity: Auditing for admins | E76: Icebox
B77: alkemio | C77: Epic,Product Discussion | D77: Bucket: Guidance: Improvements | E77: Icebox | H77: 2024 Q2
B78: alkemio | C78: Epic | D78: Choral Explanations | E78: Icebox | G78: Callouts: additional contribution types | H78: 2024 Q3 | J78: TIP
B79: alkemio | C79: Epic | D79: Sharing metrics of Space activity with leads | E79: Icebox | H79: 2024 Q3
B80: alkemio | C80: Epic,Product Discussion | D80: Multiple Language Support | E80: Icebox | G80: Collaboration templates | H80: 2024 Q2
B81: alkemio | C81: Epic,Product Team,Product Discussion | D81: Innovation Flow: Definition to include goal/checklist/callouts | E81: Icebox | H81: 2024 Q3 | I81: 80
B82: alkemio | C82: Epic | D82: Integration of other online tools | E82: Icebox | H82: 2024 Q3
B83: alkemio | C83: Epic | D83: Sharing: social media | E83: Icebox | H83: 2024 Q3 | I83: 20
B84: alkemio | C84: Epic,Product Team,Product Discussion | D84: Search in Contribute page | E84: Icebox | G84: Search: Smart | H84: 2024 Q3 | I84: 20
A85: Valentin Yanakiev | B85: infrastructure-operations | C85: operations,Epic,Infrastructure | D85: Operational security analysis | E85: Icebox | H85: 2024 Q3 | I85: 20
B86: alkemio | C86: Epic | D86: Visuals on Journeys: Enhanced selection + suggested images | E86: Icebox | H86: 2024 Q3 | I86: 30
B87: alkemio | C87: Epic,Product Team | D87: Hide / turn functionalities off | E87: Icebox | H87: 2024 Q3
B88: alkemio | C88: Epic,QA | D88: QA: Test suites expanded | E88: Icebox
B89: test-suites | C89: Epic,QA | D89: Vulnerability scanning | E89: Icebox
B90: alkemio | C90: Epic | D90: Governance: Security Audit + fixes | E90: Icebox
B91: alkemio | C91: Epic,Roadmap Candidate | D91: Database: Robust deletions | E91: Icebox
B92: alkemio | C92: Epic | D92: Bucket: Innovation flows | E92: Icebox
A93: Valentin Yanakiev,Donna | B93: alkemio | C93: Epic,Product Discussion | D93: Authentication: Support for public sector identities | E93: In progress | F93: 2025-09-16 | G93: Improved Confidence in the Platform
A94: Vladimir Aleksiev | B94: alkemio | C94: Epic | D94: VC: Enable prototyping | E94: In progress | F94: 2025-09-16
A95: Bobby Kolev | B95: alkemio | C95: Epic | D95: Notifications: InApp full set of events | E95: In progress | F95: 2025-09-16 | G95: Notifications: on the platform, per space
B96: alkemio | C96: Epic | D96: Incident Response Protocol and Improvements | E96: In progress | F96: 2025-10-14
B97: alkemio | C97: Epic | D97: Infrastructure: Maintainability Q2 2025 | E97: In progress
B98: alkemio | C98: Epic,Atlas Team | D98: Server: robustness + performance Q2 2025 | E98: In progress | G98: Improved Confidence in the Platform
A99: Valentin Yanakiev | B99: alkemio | C99: Epic | D99: Release mgmt: Process + tooling | E99: In progress | G99: Improved Confidence in the Platform | H99: 2024 Q2 | I99: 50
A100: Carlos Cano | B100: alkemio | C100: Epic | D100: Callouts: updated UI/UX | E100: New | F100: 2025-09-16
A101: Bobby Kolev | B101: alkemio | C101: Epic | D101: Template pack: UI improvements | E101: New | F101: 2025-09-16
A102: Bobby Kolev | B102: alkemio | C102: Epic | D102: Extend set of events for notifications (inapp + email) | E102: New | F102: 2025-09-16
B103: alkemio | C103: Epic | D103: Innovation Flow: settings and default callout content | E103: New | F103: 2025-09-30 | L103: Core Capabilities
...
